colorama/__init__.py
colorama/ansi.py
colorama/ansitowin32.py
colorama/initialise.py
colorama/win32.py
colorama/winterm.py
psutil/__init__.py
psutil/_common.py
psutil/_compat.py
psutil/_psaix.py
psutil/_psbsd.py
psutil/_pslinux.py
psutil/_psosx.py
psutil/_psposix.py
psutil/_pssunos.py
psutil/_pswindows.py
psutil/tests/__init__.py
psutil/tests/__main__.py
psutil/tests/runner.py
psutil/tests/test_aix.py
psutil/tests/test_bsd.py
psutil/tests/test_connections.py
psutil/tests/test_contracts.py
psutil/tests/test_linux.py
psutil/tests/test_memleaks.py
psutil/tests/test_misc.py
psutil/tests/test_osx.py
psutil/tests/test_posix.py
psutil/tests/test_process.py
psutil/tests/test_sunos.py
psutil/tests/test_system.py
psutil/tests/test_testutils.py
psutil/tests/test_unicode.py
psutil/tests/test_windows.py
ptop.py-2.1.1.dist-info/LICENSE
ptop.py-2.1.1.dist-info/METADATA
ptop.py-2.1.1.dist-info/WHEEL
ptop.py-2.1.1.dist-info/top_level.txt
ptop.py-2.1.1.dist-info/RECORD
