Metadata-Version: 2.1
Name: ptop.py
Version: 2.1.1
Summary: View System Processes
Home-page: https://github.com/DWhirlpool/ptop
Author: dwhirlpool
Author-email: ludaniel@apps.singapore.edu.hk
License: UNKNOWN
Platform: UNKNOWN
Classifier: Programming Language :: Python :: 3
Classifier: License :: OSI Approved :: MIT License
Classifier: Operating System :: OS Independent
Requires-Python: >=3.6
License-File: LICENSE
Requires-Dist: psutil
Requires-Dist: colorama
